{
    "apiVersion": 1,
    "key": "aava-description-refiner",
    "name": "AAVA Description Refiner",
    "description": "Refine Jira issue descriptions using Gemini AI",
    "vendor": {
        "name": "AAVA",
        "url": "https://example.com"
    },
    "baseUrl": "https://jira-connect-app.onrender.com",
    "links": {
        "self": "https://jira-connect-app.onrender.com/atlassian-connect.json"
    },
    "authentication": {
        "type": "jwt"
    },
    "apiMigrations": {
        "context-qsh": true
    },
    "lifecycle": {
        "installed": "/installed"
    },
    "scopes": [
        "READ",
        "WRITE"
    ],
    "modules": {
        "webPanels": [
            {
                "key": "aava-refiner-panel",
                "location": "atl.jira.view.issue.right.context",
                "name": {
                    "value": "Refine with AAVA"
                },
                "url": "/render-refiner?issueKey={issue.key}"
            }
        ]
    }
}